UliSerial/Exceptions.py
UliSerial/Find.py
UliSerial/Printer3D/Marlin.py
UliSerial/Printer3D/__init__.py
UliSerial/__init__.py
uliserial-0.2.0.dist-info/LICENSE
uliserial-0.2.0.dist-info/METADATA
uliserial-0.2.0.dist-info/WHEEL
uliserial-0.2.0.dist-info/RECORD
