Metadata-Version: 2.1
Name: UliSerial
Version: 0.2.0
Summary: Serial port utilities to save time with your electronics projects
License: Apache License v2.0
Author: Uli Köhler
Author-email: github@techoverflow.net
Requires-Python: >=3.5,<4.0
Classifier: License :: Other/Proprietary License
Classifier: Programming Language :: Python :: 3
Classifier: Programming Language :: Python :: 3.5
Classifier: Programming Language :: Python :: 3.6
Classifier: Programming Language :: Python :: 3.7
Classifier: Programming Language :: Python :: 3.8
Classifier: Programming Language :: Python :: 3.9
Classifier: Programming Language :: Python :: 3.10
Classifier: Programming Language :: Python :: 3.11
Classifier: Programming Language :: Python :: 3.12
Requires-Dist: pyserial (>=3.0,<4.0)
